nirfmxnr/__init__.py
nirfmxnr/acp.py
nirfmxnr/acp_component_carrier_configuration.py
nirfmxnr/acp_component_carrier_results.py
nirfmxnr/acp_configuration.py
nirfmxnr/acp_results.py
nirfmxnr/attributes.py
nirfmxnr/chp.py
nirfmxnr/chp_component_carrier_configuration.py
nirfmxnr/chp_component_carrier_results.py
nirfmxnr/chp_configuration.py
nirfmxnr/chp_results.py
nirfmxnr/component_carrier.py
nirfmxnr/enums.py
nirfmxnr/errors.py
nirfmxnr/examples/nirfmxnr_acp_single_carrier.py
nirfmxnr/examples/nirfmxnr_chp_single_carrier.py
nirfmxnr/examples/nirfmxnr_modacc_single_carrier.py
nirfmxnr/examples/nirfmxnr_sem_single_carrier.py
nirfmxnr/examples/nirfmxnr_ul_pvt_single_carrier_grpc.py
nirfmxnr/grpc_session_options.py
nirfmxnr/internal/_custom_types.py
nirfmxnr/internal/_grpc_stub_interpreter.py
nirfmxnr/internal/_helper.py
nirfmxnr/internal/_library.py
nirfmxnr/internal/_library_interpreter.py
nirfmxnr/internal/_library_singleton.py
nirfmxnr/internal/nidevice_pb2.py
nirfmxnr/internal/nidevice_pb2_grpc.py
nirfmxnr/internal/nirfmxnr_pb2.py
nirfmxnr/internal/nirfmxnr_pb2_grpc.py
nirfmxnr/internal/session_pb2.py
nirfmxnr/internal/session_pb2_grpc.py
nirfmxnr/modacc.py
nirfmxnr/modacc_configuration.py
nirfmxnr/modacc_results.py
nirfmxnr/nr.py
nirfmxnr/obw.py
nirfmxnr/obw_configuration.py
nirfmxnr/obw_results.py
nirfmxnr/pvt.py
nirfmxnr/pvt_configuration.py
nirfmxnr/pvt_results.py
nirfmxnr/sem.py
nirfmxnr/sem_component_carrier_configuration.py
nirfmxnr/sem_component_carrier_results.py
nirfmxnr/sem_configuration.py
nirfmxnr/sem_results.py
nirfmxnr/txp.py
nirfmxnr/txp_configuration.py
nirfmxnr/txp_results.py
nirfmxnr-26.0.0.dist-info/licenses/LICENSE
nirfmxnr-26.0.0.dist-info/METADATA
nirfmxnr-26.0.0.dist-info/WHEEL
nirfmxnr-26.0.0.dist-info/RECORD
