Metadata-Version: 2.4
Name: nirfmxnr
Version: 26.0.0
Summary: Python APIs for interacting with NI RFmx NR Product
License: MIT
License-File: LICENSE
Keywords: rfmx,nirfmx,nirfmxnr
Author: NI
Author-email: opensource@ni.com
Maintainer: Thangam V
Maintainer-email: thangam.v@emerson.com
Requires-Python: >=3.9,<4.0
Classifier: Development Status :: 4 - Beta
Classifier: Intended Audience :: Developers
Classifier: Intended Audience :: Manufacturing
Classifier: Intended Audience :: Science/Research
Classifier: License :: OSI Approved :: MIT License
Classifier: Operating System :: Microsoft :: Windows
Classifier: Programming Language :: Python :: 3
Classifier: Programming Language :: Python :: 3.9
Classifier: Programming Language :: Python :: 3.10
Classifier: Programming Language :: Python :: 3.11
Classifier: Programming Language :: Python :: 3.12
Classifier: Programming Language :: Python :: 3.13
Classifier: Programming Language :: Python :: 3.14
Classifier: Programming Language :: Python :: Implementation :: CPython
Classifier: Programming Language :: Python :: Implementation :: PyPy
Classifier: Topic :: Scientific/Engineering :: Instrument Drivers
Provides-Extra: dev
Requires-Dist: fasteners (>=0.19)
Requires-Dist: hightime (>=0.2.2)
Requires-Dist: nirfmxinstr (==26.0.0)
Requires-Dist: numpy (>=1.22) ; python_version >= "3.9" and python_version < "3.12" and implementation_name != "pypy"
Requires-Dist: numpy (>=1.26) ; implementation_name != "pypy" and python_version == "3.12"
Requires-Dist: numpy (>=2.1) ; implementation_name == "pypy" and python_version == "3.10"
Requires-Dist: numpy (>=2.1) ; python_version >= "3.13" and python_version < "4.0" and implementation_name != "pypy"
Requires-Dist: numpy (>=2.3) ; python_version >= "3.11" and python_version < "4.0" and implementation_name == "pypy"
Project-URL: Documentation, https://nirfmx-python-nirfmxnr.readthedocs-hosted.com/
Project-URL: Repository, https://github.com/ni/nirfmx-python
